Metadata-Version: 2.1
Name: cloudgenix-tenant-acl
Version: 1.0.0b1
Summary: Scripts to Download, Upload, and Optimize a CloudGenix Tenant Access List.
Home-page: https://github.com/ebob9/cloudgenix_tenant_acl
Author: Aaron Edwards
Author-email: cloudgenix_tenant_acl@ebob9.com
License: MIT
Platform: UNKNOWN
Classifier: Development Status :: 4 - Beta
Classifier: Intended Audience :: Developers
Classifier: License :: OSI Approved :: MIT License
Classifier: Programming Language :: Python :: 2.7
Classifier: Programming Language :: Python :: 3.6
Classifier: Programming Language :: Python :: 3.7
Classifier: Programming Language :: Python :: 3.8
